zuora_aqua_client_cli/__init__.py
zuora_aqua_client_cli/api.py
zuora_aqua_client_cli/cli.py
zuora_aqua_client_cli/consts.py
zuora_aqua_client_cli-1.4.0.dist-info/entry_points.txt
zuora_aqua_client_cli-1.4.0.dist-info/LICENSE
zuora_aqua_client_cli-1.4.0.dist-info/WHEEL
zuora_aqua_client_cli-1.4.0.dist-info/METADATA
zuora_aqua_client_cli-1.4.0.dist-info/RECORD
