Metadata-Version: 2.1
Name: zuora-aqua-client-cli
Version: 1.4.0
Summary: Run ZOQL queries through AQuA from the command line
Home-page: https://github.com/molnarjani/zuora-aqua-client-cli
Keywords: Zuora,ZOQL
Author: Janos Molnar
Author-email: janosmolnar1001@gmail.com
Requires-Python: >=3.6,<4.0
Classifier: Programming Language :: Python :: 3
Classifier: Programming Language :: Python :: 3.6
Classifier: Programming Language :: Python :: 3.7
Classifier: Programming Language :: Python :: 3.8
Requires-Dist: click (>=7.0,<8.0)
Requires-Dist: flake8 (>=3.7,<4.0)
Requires-Dist: requests (>=2.22,<3.0)
Project-URL: Repository, https://github.com/molnarjani/zuora-aqua-client-cli
